flaskz/__init__.py
flaskz/res_status_codes.py
flaskz/auth/__init__.py
flaskz/auth/_jws.py
flaskz/ext/__init__.py
flaskz/ext/cypher.py
flaskz/ext/ssh.py
flaskz/log/__init__.py
flaskz/models/__init__.py
flaskz/models/_base.py
flaskz/models/_model.py
flaskz/models/_query_util.py
flaskz/models/_util.py
flaskz/rest/__init__.py
flaskz/rest/_mgmt.py
flaskz/rest/_util.py
flaskz/utils/__init__.py
flaskz/utils/_app.py
flaskz/utils/_cache.py
flaskz/utils/_cls.py
flaskz/utils/_common.py
flaskz/utils/_func.py
flaskz/utils/_magic.py
flaskz/utils/_private.py
flaskz/utils/_request_api.py
flaskz/utils/_request_args.py
flaskz/utils/_response.py
flaskz/utils/_timer.py
flaskz-1.8.3.dist-info/licenses/LICENSE
flaskz-1.8.3.dist-info/METADATA
flaskz-1.8.3.dist-info/WHEEL
flaskz-1.8.3.dist-info/top_level.txt
flaskz-1.8.3.dist-info/RECORD
