Metadata-Version: 2.4
Name: flaskz
Version: 1.8.3
Summary: Flask and SQLAlchemy extensions for web applications
Home-page: https://github.com/taozh1982/flaskz
Author: Zhang Tao
Author-email: taozh1982@gmail.com
Project-URL: Bug Tracker, https://github.com/taozh1982/flaskz/issues
Classifier: Programming Language :: Python :: 3
Classifier: License :: OSI Approved :: MIT License
Classifier: Operating System :: OS Independent
Requires-Python: >=3.6
License-File: LICENSE
Requires-Dist: Flask>=1.1.1
Requires-Dist: SQLAlchemy>=1.4.0
Requires-Dist: requests>=2
Provides-Extra: ext
Requires-Dist: pycryptodome>=3.15.0; extra == "ext"
Requires-Dist: paramiko>=3.0.0; extra == "ext"
Dynamic: license-file
